[{"data":{"id":"Install-ReportUnit","source":null,"target":null}},{"data":{"id":"3949333a-b32f-4578-a65d-04717a6fdd85","source":"Install-ReportUnit","target":"Install-ReportGenerator"}},{"data":{"id":"Install-ReportGenerator","source":null,"target":null}},{"data":{"id":"54304ab5-c9b6-4710-b090-0ebb3295b5ff","source":"Install-ReportGenerator","target":"DotNetCore-Build"}},{"data":{"id":"DotNetCore-Build","source":null,"target":null}},{"data":{"id":"ab15c8f2-e898-4515-b8fb-8e89e6dc00fa","source":"DotNetCore-Build","target":"Clean"}},{"data":{"id":"04fd0a65-86df-4d8f-a432-4a1441678fa7","source":"DotNetCore-Build","target":"DotNetCore-Restore"}},{"data":{"id":"DotNetCore-Restore","source":null,"target":null}},{"data":{"id":"Clean","source":null,"target":null}},{"data":{"id":"8b186a31-bc0a-4de3-835a-18718f617437","source":"Clean","target":"Show-Info"}},{"data":{"id":"59a4ed8d-98c5-4c6b-8558-30ed193c24f4","source":"Clean","target":"Print-AppVeyor-Environment-Variables"}},{"data":{"id":"Print-AppVeyor-Environment-Variables","source":null,"target":null}},{"data":{"id":"Show-Info","source":null,"target":null}}]